seba/__init__.py
seba/py.typed
seba/version.py
seba-0.1.0.dist-info/LICENSE
seba-0.1.0.dist-info/METADATA
seba-0.1.0.dist-info/WHEEL
seba-0.1.0.dist-info/top_level.txt
seba-0.1.0.dist-info/RECORD
